{
    "data": {
        "playerProfileCareer": {
            "playerId": "11779",
            "tourCode": "R",
            "events": "64",
            "wins": "",
            "winsTitle": "PGA TOUR WINS",
            "internationalWins": "0",
            "majorWins": null,
            "cutsMade": "37/64",
            "runnerUp": "",
            "second": "",
            "third": "",
            "top10": "3",
            "top25": "10",
            "years": [
                {
                    "cutsMade": "-",
                    "displaySeason": "1980",
                    "events": "3",
                    "officialMoney": "-",
                    "second": "-",
                    "standingsPoints": "-",
                    "standingsRank": "-",
                    "third": "-",
                    "top10": "-",
                    "top25": "-",
                    "tourCode": "R",
                    "wins": "-",
                    "withdrawn": "-",
                    "year": 1980
                },
                {
                    "cutsMade": "2",
                    "displaySeason": "1979",
                    "events": "7",
                    "officialMoney": "1,923",
                    "second": "-",
                    "standingsPoints": "-",
                    "standingsRank": "-",
                    "third": "-",
                    "top10": "-",
                    "top25": "-",
                    "tourCode": "R",
                    "wins": "-",
                    "withdrawn": "-",
                    "year": 1979
                },
                {
                    "cutsMade": "7",
                    "displaySeason": "1978",
                    "events": "12",
                    "officialMoney": "15,921",
                    "second": "-",
                    "standingsPoints": "-",
                    "standingsRank": "-",
                    "third": "-",
                    "top10": "1",
                    "top25": "4",
                    "tourCode": "R",
                    "wins": "-",
                    "withdrawn": "-",
                    "year": 1978
                },
                {
                    "cutsMade": "10",
                    "displaySeason": "1977",
                    "events": "16",
                    "officialMoney": "14,510",
                    "second": "-",
                    "standingsPoints": "-",
                    "standingsRank": "-",
                    "third": "-",
                    "top10": "1",
                    "top25": "2",
                    "tourCode": "R",
                    "wins": "-",
                    "withdrawn": "-",
                    "year": 1977
                },
                {
                    "cutsMade": "7",
                    "displaySeason": "1976",
                    "events": "11",
                    "officialMoney": "6,895",
                    "second": "-",
                    "standingsPoints": "-",
                    "standingsRank": "-",
                    "third": "-",
                    "top10": "-",
                    "top25": "2",
                    "tourCode": "R",
                    "wins": "-",
                    "withdrawn": "-",
                    "year": 1976
                },
                {
                    "cutsMade": "10",
                    "displaySeason": "1975",
                    "events": "14",
                    "officialMoney": "8,497",
                    "second": "-",
                    "standingsPoints": "-",
                    "standingsRank": "-",
                    "third": "-",
                    "top10": "1",
                    "top25": "1",
                    "tourCode": "R",
                    "wins": "-",
                    "withdrawn": "-",
                    "year": 1975
                },
                {
                    "cutsMade": "1",
                    "displaySeason": "1974",
                    "events": "1",
                    "officialMoney": "1,633",
                    "second": "-",
                    "standingsPoints": "-",
                    "standingsRank": "-",
                    "third": "-",
                    "top10": "-",
                    "top25": "1",
                    "tourCode": "R",
                    "wins": "-",
                    "withdrawn": "-",
                    "year": 1974
                }
            ],
            "officialMoney": "$51,895",
            "tourPills": [
                {
                    "tourCode": null,
                    "displayName": "All"
                },
                {
                    "tourCode": "R",
                    "displayName": "PGATOUR"
                }
            ],
            "achievements": [
                {
                    "title": "Events Played",
                    "value": "64"
                },
                {
                    "title": "PGA TOUR WINS",
                    "value": "0"
                },
                {
                    "title": "International Wins",
                    "value": "0"
                },
                {
                    "title": "Cuts Made",
                    "value": "37/64"
                },
                {
                    "title": "Runner Up",
                    "value": "0"
                },
                {
                    "title": "Third Place Finishes",
                    "value": "0"
                },
                {
                    "title": "Top 5 Finishes",
                    "value": "2"
                },
                {
                    "title": "Top 10 Finishes",
                    "value": "3"
                },
                {
                    "title": "Year Joined Tour",
                    "value": "-"
                },
                {
                    "title": "Official Money",
                    "value": "$51,895"
                }
            ],
            "tables": []
        }
    }
}